expressionive/__init__.py
expressionive/expressionive.py
expressionive/expridioms.py
expressionive/exprpages.py
expressionive-0.0.11.dist-info/LICENSE
expressionive-0.0.11.dist-info/WHEEL
expressionive-0.0.11.dist-info/METADATA
expressionive-0.0.11.dist-info/RECORD
