Metadata-Version: 2.1
Name: expressionive
Version: 0.0.11
Summary: A Python3-compatible fork of 'Throw out your templates', similar to Nevow's 'stan'.
Author-email: "John C. G. Sturdy" <jcg.sturdy@gmail.com>
Classifier: License :: OSI Approved :: GNU General Public License v3 or later (GPLv3+)
